[
  {
    "id": 1,
    "name": "Arena Hash - Cómo te va mi amor.m4a",
    "duration": 329.584036,
    "url": "blob:http://localhost/9383400b-4772-458f-9540-f1241873328a",
    "size": 5334819,
    "type": "audio/mp4"
  },
  {
    "id": 2,
    "name": "Pedro Suárez Vértiz - Alguien que bese como tú.m4a",
    "duration": 210.581768,
    "url": "blob:http://localhost/208cc508-67be-4ccc-987f-8e21a2c4aaa2",
    "size": 3408891,
    "type": "audio/mp4"
  },
  {
    "id": 3,
    "name": "Pedro Suárez Vértiz - Como las mariposas.m4a",
    "duration": 235.47356,
    "url": "blob:http://localhost/8844977f-6f9e-48d3-a4a7-4b52e5e89481",
    "size": 3811679,
    "type": "audio/mp4"
  },
  {
    "id": 4,
    "name": "Pedro Suárez Vértiz - Cuéntame.m4a",
    "duration": 233.151564,
    "url": "blob:http://localhost/23b3f191-fad1-4f29-ae29-c7f23573bb42",
    "size": 3774128,
    "type": "audio/mp4"
  },
  {
    "id": 5,
    "name": "Pedro Suárez Vértiz - Me elevé.m4a",
    "duration": 220.357369,
    "url": "blob:http://localhost/dabef6b4-e511-4bd1-961b-023af4bed8d8",
    "size": 3567100,
    "type": "audio/mp4"
  },
  {
    "id": 6,
    "name": "Pedro Suárez Vértiz - Me resfrié en Brasil.m4a",
    "duration": 230.38839,
    "url": "blob:http://localhost/33111094-672b-4bda-a084-76f195a9308f",
    "size": 3729441,
    "type": "audio/mp4"
  },
  {
    "id": 7,
    "name": "Pedro Suárez Vértiz - No llores más.m4a",
    "duration": 235.68,
    "url": "blob:http://localhost/ef214fb3-d2a3-4931-a78d-71cc759e8bdc",
    "size": 3816890,
    "type": "audio/mp4"
  },
  {
    "id": 8,
    "name": "Pedro Suárez Vértiz - No pensé que era amor.m4a",
    "duration": 233.04,
    "url": "blob:http://localhost/efb60bc6-6fd1-40a1-98ef-33876e594cf6",
    "size": 3773625,
    "type": "audio/mp4"
  },
  {
    "id": 9,
    "name": "Pedro Suárez Vértiz - Sé que todo ha acabado ya.m4a",
    "duration": 220.473469,
    "url": "blob:http://localhost/69ed3b0b-04c8-474c-9e39-4534a6f86794",
    "size": 3568978,
    "type": "audio/mp4"
  },
  {
    "id": 10,
    "name": "Pedro Suárez Vértiz - Sentimiento increíble.m4a",
    "duration": 206.332517,
    "url": "blob:http://localhost/24c2931d-8f07-46d8-84cc-cf64634204d4",
    "size": 3340055,
    "type": "audio/mp4"
  },
  {
    "id": 11,
    "name": "Pedro Suárez Vértiz - Si escuchas a un angel.m4a",
    "duration": 181.44,
    "url": "blob:http://localhost/538ae226-0484-437c-a4d4-081b3dcbd925",
    "size": 2938353,
    "type": "audio/mp4"
  },
  {
    "id": 12,
    "name": "Pedro Suárez Vértiz - Talk show.m4a",
    "duration": 354.573333,
    "url": "blob:http://localhost/2d58d939-5541-48e3-929e-b01c025ebf1d",
    "size": 5741049,
    "type": "audio/mp4"
  },
  {
    "id": 13,
    "name": "Pedro Suárez Vértiz - Te siento de sólo pensar.m4a",
    "duration": 202.408344,
    "url": "blob:http://localhost/e477a9a7-2cc7-47e8-a7d0-b5538af84baa",
    "size": 3276501,
    "type": "audio/mp4"
  },
  {
    "id": 14,
    "name": "Virus - Amor descartable.m4a",
    "duration": 212.021405,
    "url": "blob:http://localhost/edb74653-8baa-4907-900d-988d45bc4d53",
    "size": 3432173,
    "type": "audio/mp4"
  },
  {
    "id": 15,
    "name": "Virus - Dame una señal.m4a",
    "duration": 238.399274,
    "url": "blob:http://localhost/1e2bade7-e8cb-445a-909b-b21b0657f3f7",
    "size": 3858904,
    "type": "audio/mp4"
  },
  {
    "id": 16,
    "name": "Virus - Imágenes paganas.m4a",
    "duration": 270.651791,
    "url": "blob:http://localhost/5c14063a-f211-4cb1-b6bc-2184e996a216",
    "size": 4381055,
    "type": "audio/mp4"
  },
  {
    "id": 17,
    "name": "Virus - Luna de miel en la mano.m4a",
    "duration": 318.020498,
    "url": "blob:http://localhost/4f09ea21-a617-4295-b480-016a597aab51",
    "size": 5147578,
    "type": "audio/mp4"
  },
  {
    "id": 18,
    "name": "Virus - Polvos de una relación.m4a",
    "duration": 219.312471,
    "url": "blob:http://localhost/d2f1391f-1051-4e7f-a730-c8ade7c7011b",
    "size": 3549995,
    "type": "audio/mp4"
  },
  {
    "id": 19,
    "name": "Virus - Pronta entrega.m4a",
    "duration": 274.901043,
    "url": "blob:http://localhost/3c4d299d-0a15-4928-89e7-14f4a9d25e80",
    "size": 4449684,
    "type": "audio/mp4"
  },
  {
    "id": 20,
    "name": "Virus - Sin disfraz.m4a",
    "duration": 330.303854,
    "url": "blob:http://localhost/47979e0d-285e-4c26-977c-8e70788142eb",
    "size": 5346369,
    "type": "audio/mp4"
  }
]